arithmeticPackageOwais/__init__.py
arithmeticPackageOwais/addition.py
arithmeticPackageOwais/example.py
arithmeticPackageOwais/multiplication.py
arithmeticPackageOwais/subtraction.py
arithmeticTestPackage_owais_md-0.0.2.dist-info/LICENSE
arithmeticTestPackage_owais_md-0.0.2.dist-info/METADATA
arithmeticTestPackage_owais_md-0.0.2.dist-info/WHEEL
arithmeticTestPackage_owais_md-0.0.2.dist-info/top_level.txt
arithmeticTestPackage_owais_md-0.0.2.dist-info/RECORD
