Metadata-Version: 2.1
Name: arithmeticTestPackage-owais-md
Version: 0.0.2
Summary: Simple arithmetic package
Author-email: Owais <mohammad.owais@iiitb.ac.in>
Classifier: Programming Language :: Python :: 3
Classifier: License :: OSI Approved :: MIT License
Classifier: Operating System :: OS Independent
Requires-Python: >=3.6
License-File: LICENSE
